setup.cfg
setup.py
dnaseq_queue_status/__init__.py
dnaseq_queue_status/__main__.py
dnaseq_queue_status/main.py
dnaseq_queue_status.egg-info/PKG-INFO
dnaseq_queue_status.egg-info/SOURCES.txt
dnaseq_queue_status.egg-info/dependency_links.txt
dnaseq_queue_status.egg-info/entry_points.txt
dnaseq_queue_status.egg-info/requires.txt
dnaseq_queue_status.egg-info/top_level.txt