Metadata-Version: 1.1
Name: dnaseq-queue-status
Version: 0.7
Summary: write db status
Home-page: https://github.com/jeremiahsavage/dnaseq_queue_status
Author: Jeremiah H. Savage
Author-email: jeremiahsavage@gmail.com
License: Apache 2.0
Platform: UNKNOWN
Classifier: Development Status :: 3 - Alpha
Classifier: Intended Audience :: Developers
Classifier: License :: OSI Approved :: Apache Software License
Classifier: Programming Language :: Python
Classifier: Programming Language :: Python :: 2
Classifier: Programming Language :: Python :: 3
